secure_imaplib/__init__.py
secure_imaplib-0.1.2.dist-info/metadata.json
secure_imaplib-0.1.2.dist-info/zip-safe
secure_imaplib-0.1.2.dist-info/WHEEL
secure_imaplib-0.1.2.dist-info/top_level.txt
secure_imaplib-0.1.2.dist-info/METADATA
secure_imaplib-0.1.2.dist-info/DESCRIPTION.rst
secure_imaplib-0.1.2.dist-info/RECORD
