Metadata-Version: 2.0
Name: secure-imaplib
Version: 0.1.2
Summary: Secure IMAP subclasses for Python 2
Home-page: https://github.com/graingert/secure-imaplib
Author: Thomas Grainger
Author-email: secure-imaplib@graingert.co.uk
License: UNKNOWN
Keywords: imaplib,TLS,SSL,verify,validate,ca_cert,ca
Platform: UNKNOWN
